twitter_activity_api_dummy/activity_manager/activity_identifier.py
twitter_activity_api_dummy/activity_manager/resources.py
twitter_activity_api_dummy/activity_manager/save_manager.py
twitter_activity_api_dummy/activity_manager/save_to_folder.py
twitter_activity_api_dummy/activity_manager/save_to_s3.py
twitter_activity_api_dummy/webhook_manager/twitter_webhook_manager.py
twitter_activity_api_dummy-0.0.3.dist-info/LICENSE
twitter_activity_api_dummy-0.0.3.dist-info/METADATA
twitter_activity_api_dummy-0.0.3.dist-info/WHEEL
twitter_activity_api_dummy-0.0.3.dist-info/top_level.txt
twitter_activity_api_dummy-0.0.3.dist-info/RECORD
