Metadata-Version: 2.1
Name: twitter-activity-api-dummy
Version: 0.0.3
Summary: This library is to help you work with web-hook, Classify twitter account activities and save these activities 
Home-page: https://github.com/Samer92/twitter_activity_api_dummy
Author: sammer sallam
Author-email: samersallam92@gmail.com
License: UNKNOWN
Platform: UNKNOWN
Classifier: Programming Language :: Python :: 3
Classifier: License :: OSI Approved :: MIT License
Classifier: Operating System :: OS Independent
Requires-Python: >=3.6
Requires-Dist: aws-s3-resource (==0.0.2)
Requires-Dist: boto3 (==1.12.43)
Requires-Dist: botocore (==1.15.43)
Requires-Dist: docutils (==0.15.2)
Requires-Dist: jmespath (==0.9.5)
Requires-Dist: python-dateutil (==2.8.1)
Requires-Dist: s3transfer (==0.3.3)
Requires-Dist: six (==1.14.0)
Requires-Dist: urllib3 (==1.25.9)
Requires-Dist: certifi (==2020.4.5.1)
Requires-Dist: chardet (==3.0.4)
Requires-Dist: idna (==2.9)
Requires-Dist: oauthlib (==3.1.0)
Requires-Dist: PySocks (==1.7.1)
Requires-Dist: requests (==2.23.0)
Requires-Dist: requests-oauthlib (==1.3.0)
Requires-Dist: tweepy (==3.8.0)
